Oasys/PRIMER/__init__.py
Oasys/PRIMER/accelerometer.py
Oasys/PRIMER/airbag.py
Oasys/PRIMER/attached.py
Oasys/PRIMER/axialforcebeam.py
Oasys/PRIMER/beam.py
Oasys/PRIMER/belt.py
Oasys/PRIMER/box.py
Oasys/PRIMER/colour.py
Oasys/PRIMER/comment.py
Oasys/PRIMER/connectionproperties.py
Oasys/PRIMER/constructionstages.py
Oasys/PRIMER/contact.py
Oasys/PRIMER/contactguidedcable.py
Oasys/PRIMER/conx.py
Oasys/PRIMER/coordinatesystem.py
Oasys/PRIMER/core.py
Oasys/PRIMER/crosssection.py
Oasys/PRIMER/curve.py
Oasys/PRIMER/dampingfrequencyrange.py
Oasys/PRIMER/dampingpartmass.py
Oasys/PRIMER/dampingpartstiffness.py
Oasys/PRIMER/dampingpartstructural.py
Oasys/PRIMER/dampingrelative.py
Oasys/PRIMER/deformabletorigid.py
Oasys/PRIMER/discrete.py
Oasys/PRIMER/discretesphere.py
Oasys/PRIMER/dummy.py
Oasys/PRIMER/elementdeath.py
Oasys/PRIMER/extranodes.py
Oasys/PRIMER/freqfrf.py
Oasys/PRIMER/freqssd.py
Oasys/PRIMER/freqvibration.py
Oasys/PRIMER/funcs.py
Oasys/PRIMER/generalizedweld.py
Oasys/PRIMER/geometrysurface.py
Oasys/PRIMER/group.py
Oasys/PRIMER/hexspotweldassembly.py
Oasys/PRIMER/history.py
Oasys/PRIMER/hourglass.py
Oasys/PRIMER/iga1dbrep.py
Oasys/PRIMER/iga1dnurbsuvw.py
Oasys/PRIMER/iga1dnurbsxyz.py
Oasys/PRIMER/iga2dbasistransformxyz.py
Oasys/PRIMER/iga2dbrep.py
Oasys/PRIMER/iga2dnurbsuvw.py
Oasys/PRIMER/iga2dnurbsxyz.py
Oasys/PRIMER/iga3dbasistransformxyz.py
Oasys/PRIMER/iga3dnurbsxyz.py
Oasys/PRIMER/igaedgeuvw.py
Oasys/PRIMER/igaedgexyz.py
Oasys/PRIMER/igafaceuvw.py
Oasys/PRIMER/igafacexyz.py
Oasys/PRIMER/igaintegrationshellreduce.py
Oasys/PRIMER/igaintegrationsolidreduce.py
Oasys/PRIMER/igamass.py
Oasys/PRIMER/igapointuvw.py
Oasys/PRIMER/igashell.py
Oasys/PRIMER/igasolid.py
Oasys/PRIMER/igavolumexyz.py
Oasys/PRIMER/image.py
Oasys/PRIMER/include.py
Oasys/PRIMER/integrationbeam.py
Oasys/PRIMER/integrationshell.py
Oasys/PRIMER/interfacecomponent.py
Oasys/PRIMER/interfacelinkingedge.py
Oasys/PRIMER/interfacespringback.py
Oasys/PRIMER/interpolation.py
oasys_primer-22.1.0.dist-info/licenses/LICENSE
oasys_primer-22.1.0.dist-info/METADATA
oasys_primer-22.1.0.dist-info/WHEEL
oasys_primer-22.1.0.dist-info/top_level.txt
oasys_primer-22.1.0.dist-info/RECORD
